pinnics/__init__.py
pinnics/grad.py
pinnics/network.py
pinnics/problem_container.py
pinnics/var_container.py
pinnics/var_spec.py
pinnics/utils/__init__.py
pinnics/utils/encode_dict_str.py
pinn_ics-1.0.1.dist-info/METADATA
pinn_ics-1.0.1.dist-info/WHEEL
pinn_ics-1.0.1.dist-info/top_level.txt
pinn_ics-1.0.1.dist-info/RECORD
